parser/__init__.py
parser/irdi_parser.py
test/__init__.py
test/test_irdi_parser.py
irdi_parser-1.0.1.dist-info/LICENSE
irdi_parser-1.0.1.dist-info/METADATA
irdi_parser-1.0.1.dist-info/WHEEL
irdi_parser-1.0.1.dist-info/top_level.txt
irdi_parser-1.0.1.dist-info/RECORD
